{
  "jogos" : [
    {
      "perguntas" : [
        {
          "pergunta" : "In what children's game are participants chased by someone designated \"It\"?",
          "conteudo" : [
            "Tag",
            "Simon Says",
            "Charades",
            "Hopscotch"
          ],
          "correta" : 0
        },
        {
          "pergunta" : "On a radio, stations are changed by using what control?",
          "conteudo" : [
            "Tuning",
            "Volume",
            "Bass",
            "Treble"
          ],
          "correta" : 0
        },
        {
          "pergunta" : "Which material is most dense?",
          "conteudo" : [
            "Silver",
            "Styrofoam",
            "Butter",
            "Gold"
          ],
          "correta" : 3
        },
        {
          "pergunta" : "Which state in the United States is largest by area?",
          "conteudo" : [
            "Alaska",
            "California",
            "Texas",
            "Hawaii"
          ],
          "correta" : 0
        },
        {
          "pergunta" : "What is Aurora Borealis commonly known as?",
          "conteudo" : [
            "Fairy Dust",
            "Northern Lights",
            "Book of ages",
            "a Game of Thrones main character"
          ],
          "correta" : 1
        },
        {
          "correta": 3,
          "conteudo": [
            "developed the telescope",
            "discovered four satellites of Jupiter",
            "discovered that the movement of pendulum produces a regular time measurement",
            "All of the above"
          ],
          "pergunta": "Galileo was an Italian astronomer who"
        }
      ]
    }
  ]
}